{
	"case_1": {"input_size": 45, "hidden_size": 25, "epochs": 600, "learning_rate": 0.011, "momentum": 0.001, "iterations": 20, "subset_size":275},
	"case_2": {"input_size": 6, "hidden_size": 4, "epochs": 300, "learning_rate": 0.1, "momentum": 0.01, "iterations": 20, "subset_size":250},
	"case_3": {"input_size": 42, "hidden_size": 25, "epochs": 600, "learning_rate": 0.001, "momentum": 0.001, "iterations": 19, "subset_size":275},
	"case_4": {"input_size": 4, "hidden_size": 3, "epochs": 500, "learning_rate": 0.2, "momentum": 0.3, "iterations": 40, "subset_size":300},
	"case_5": {"input_size": 7, "hidden_size": 25, "epochs": 500, "learning_rate": 0.09, "momentum": 0.01, "iterations": 19, "subset_size":200},
	"case_6": {"input_size": 7, "hidden_size": 4, "epochs": 300, "learning_rate": 0.09, "momentum": 0.001, "iterations": 20, "subset_size":250},
	"case_7": {"input_size": 7, "hidden_size": 4, "epochs": 300, "learning_rate": 0.09, "momentum": 0.001, "iterations": 20, "subset_size":250},
	"case_8": {"input_size": 8, "hidden_size": 4, "epochs": 300, "learning_rate": 0.09, "momentum": 0.001, "iterations": 20, "subset_size":250}
}
